tests/__init__.py
tests/test_datetime_parser.py
todocli/__init__.py
todocli/cli.py
todocli/help_msg.py
todocli/interface.py
todocli/graphapi/__init__.py
todocli/graphapi/oauth.py
todocli/graphapi/wrapper.py
todocli/models/__init__.py
todocli/models/todolist.py
todocli/models/todotask.py
todocli/utils/__init__.py
todocli/utils/datetime_util.py
todocli/utils/update_checker.py
tod0-0.7.1.dist-info/LICENSE
tod0-0.7.1.dist-info/METADATA
tod0-0.7.1.dist-info/WHEEL
tod0-0.7.1.dist-info/entry_points.txt
tod0-0.7.1.dist-info/top_level.txt
tod0-0.7.1.dist-info/RECORD
