Metadata-Version: 2.1
Name: tod0
Version: 0.7.1
Summary: A Terminal Client for Microsoft To-Do.
Home-page: https://github.com/kiblee/tod0
Author: kiblee
Author-email: kiblee@pm.me
License: LICENSE
Requires-Python: >=3.6
License-File: LICENSE
Requires-Dist: prompt-toolkit (>=3.0.31)
Requires-Dist: pyyaml
Requires-Dist: requests (>=2.28.1)
Requires-Dist: requests-oauthlib
Requires-Dist: bs4
Requires-Dist: yaspin (>=2.2.0)
